zia/__init__.py
zia/__main__.py
zia/activation.py
zia/admin_audit_logs.py
zia/admin_role_management.py
zia/cloud_sandbox_report.py
zia/data/config.yaml
zia/datacenters.py
zia/defaults.py
zia/firewall.py
zia/gre.py
zia/helpers.py
zia/locations.py
zia/sandbox.py
zia/security.py
zia/session.py
zia/ssl_inspection_settings.py
zia/traffic_forwarding.py
zia/url_categories.py
zia/url_filtering_policies.py
zia/user_authentication_settings.py
zia/user_management.py
zia/zscaler_internet_access.py
zia-0.1.4.dist-info/entry_points.txt
zia-0.1.4.dist-info/LICENSE
zia-0.1.4.dist-info/WHEEL
zia-0.1.4.dist-info/METADATA
zia-0.1.4.dist-info/RECORD
