Metadata-Version: 2.1
Name: zia
Version: 0.1.4
Summary: Zscaler Internet Access CLI
Home-page: https://github.com/omitroom13
License: MIT
Author: omitroom13
Requires-Python: >=3.8,<4.0
Classifier: License :: OSI Approved :: MIT License
Classifier: Programming Language :: Python :: 3
Classifier: Programming Language :: Python :: 3.8
Classifier: Programming Language :: Python :: 3.9
Requires-Dist: PyYAML (>=5.3.1,<6.0.0)
Requires-Dist: fire (>=0.3.1,<0.4.0)
Requires-Dist: requests (>=2.24.0,<3.0.0)
Project-URL: Repository, https://github.com/omitroom13/zia
